{
  "contact_title": "We'd Love to hear from You!",
  "contact_left_title": "Get in Touch",
  "contact_left_mid": "Head Office",
  "contact_left_l1": "ERIP, 1709, 1st Main Rd,",
  "contact_left_l2": "Austin Town, Neelasandra,",
  "contact_left_l3": "Bengaluru, Karnataka 560047",
  "contact_left_l4": "Tel - 080-47184455",
  "get_direction": "GET DIRECTION",
  "helpline_number": "Helpline Number",
  "helpline_no": "080-47184455",
  "time": "*10 am - 7 pm (All Days)",
  "contact_right_title": "Need Help?",
  "contact_right_para": "Fill the form below to get a callback.",
  "connect_us" :"Or Connect Us on Whatsapp"
}
